mojoperception/__init__.py
mojoperception/mojo_perception_api.py
mojoperception-2.0.0.dist-info/LICENSE
mojoperception-2.0.0.dist-info/METADATA
mojoperception-2.0.0.dist-info/WHEEL
mojoperception-2.0.0.dist-info/top_level.txt
mojoperception-2.0.0.dist-info/RECORD
