Metadata-Version: 2.1
Name: mojoperception
Version: 2.0.0
Summary: Mojo Perception Python API
Home-page: https://mojo.ai
Author: Hoomano
Author-email: contact@hoomano.com
Project-URL: Git, https://github.com/hoomano/mojo-perception-python
Classifier: Programming Language :: Python :: 3
Classifier: License :: OSI Approved :: MIT License
Classifier: Operating System :: OS Independent
Requires-Python: >=3.6
License-File: LICENSE
Requires-Dist: mediapipe
Requires-Dist: opencv-python
Requires-Dist: python-socketio
Requires-Dist: websocket-client
Requires-Dist: requests
